{
  "userEmail": "testportalfreeaccount30995@mailinator.com",
  "password": "Test@123",
  "username": "Satish Automation",
  "emailVerificationURL": "https://www.mailinator.com/v4/public/inboxes.jsp?to=",
  "successfulMessageForForgotPassword": "Thank you. You will receive an email with a password reset link if this account is registered.",
  "fromEmail": "noreply@mg.cogmento.com",
  "newPasswordForReset": "Test@123",
  "successfulMessageForPasswordReset": "You have successfully changed your password.\nClick here to log in.",
  "signupEmail": "user@mailinator.com"
}